{
    "budget": [
        {
            "title": "Take-out",
            "amount": 30, 
            "color": "#98abc5"
        }, 
        {
            "title": "Grocery",
            "amount": 90,
            "color": "#8a89a6" 
        
        }, 
        {
            "title": "Rent",
            "amount": 650,
            "color": "#7b6888" 
        }, 
        {
            "title": "Utilities",
            "amount": 100,
            "color": "#6b486b" 
        }, 
        {
            "title": "Prescription",
            "amount": 50,
            "color": "#a05d56"
        }, 
        {
            "title": "Gas",
            "amount": 100,
            "color": "#d0743c" 
        }, 
        {
            "title": "Entertainment",
            "amount": 30,
            "color":"#ff8c00"
        }
    ]
}
    